smelly_tokens/__init__.py
smelly_tokens/models.py
smelly_tokens/test_smelly_tokens.py
smelly_tokens/tests.py
smelly_tokens/urls.py
django_smelly_tokens-0.5.0.dist-info/METADATA
django_smelly_tokens-0.5.0.dist-info/WHEEL
django_smelly_tokens-0.5.0.dist-info/top_level.txt
django_smelly_tokens-0.5.0.dist-info/zip-safe
django_smelly_tokens-0.5.0.dist-info/RECORD
