Metadata-Version: 2.1
Name: django-smelly-tokens
Version: 0.5.0
Summary: Code quality tests
Home-page: https://gitlab.com/murchik/django-smelly-tokens
Author: murchik
Author-email: murchik@protonmail.com
License: GPLv3
Keywords: django-smelly-tokens
Platform: UNKNOWN
Classifier: Development Status :: 3 - Alpha
Classifier: Framework :: Django
Classifier: Intended Audience :: Developers
Classifier: License :: OSI Approved :: GNU General Public License v3 (GPLv3)
Classifier: Operating System :: OS Independent
Classifier: Natural Language :: English
Classifier: Programming Language :: Python :: 3
Classifier: Programming Language :: Python :: 3.4
Classifier: Programming Language :: Python :: 3.5
Classifier: Programming Language :: Python :: 3.6
Classifier: Programming Language :: Python :: 3.7
Classifier: Programming Language :: Python :: 3.8
Classifier: Programming Language :: Python :: 3.9
Classifier: Programming Language :: Python :: 3.10
Requires-Dist: Django (>=1.4)
Requires-Dist: pytest-django
